README.txt
setup.py
europeana/__init__.py
europeana/search.py
europeana_search.egg-info/PKG-INFO
europeana_search.egg-info/SOURCES.txt
europeana_search.egg-info/dependency_links.txt
europeana_search.egg-info/requires.txt
europeana_search.egg-info/top_level.txt