Metadata-Version: 1.0
Name: europeana-search
Version: 0.1.0
Summary: Basic Python wrapper for Europeana Search API.
Home-page: UNKNOWN
Author: Martin Keegan
Author-email: martin@no.ucant.org
License: LICENSE.txt
Platform: UNKNOWN
